{
  "text": "제56조(논문심사의 합격 등) ① 석사학위청구논문의 합격은 논문심사위원회 재적위원 3분의 2 이상의 찬성으 로 한다.\n② 박사학위청구논문의 합격은 논문심사위원회 재적위원 5분의 4 이상으로 한다.\n③ 논문심사에서 불합격한 자는 학위지도교수의 지도하에 수정‧보완한 후 재심사를 청구할 수 있다.",
  "metadata": {
    "document_title": "1-1. 일반대학원내규 개정 전문_2025.3.1_ek",
    "sourceFile": "1-1. 일반대학원내규 개정 전문_2025.3.1_ek.pdf",
    "page": 9,
    "articleNumber": 56,
    "articleSub": null,
    "articleTitle": "논문심사의 합격 등",
    "contentType": "text",
    "md5": "654e48c561df1f16e5ad9afa51055836",
    "page_number": 9,
    "article_number": "제56조",
    "article_title": "논문심사의 합격 등",
    "content_type": "text"
  }
}