{
  "text": "| 대상 | 구분 | 전체 인원수 | 폐과 동의 인원수 |  |\n| --- | --- | --- | --- | --- |\n|  |  |  |  | 폐과 비동의 인원수 |\n|  |  |  |  |  |\n| 교원 | 소속학과(전공) | 명 | 명 | 명 |\n| 학생 | 석사(재학+휴학) | 명 | 명 | 명 |\n|  | 박사(재학+휴학) | 명 | 명 | 명 |\n|  | 석박통합\n(재학+휴학) | 명 | 명 | 명 |\n| 상기와 같이 대학원 학과(전공) 폐과를 신청합니다.\n. . .\n____________학과장 : (인)\n____________단과대학장 : (인)\n____________대학원장 : (인)\n대학원장 귀하 |  |  |  |  |\n| 붙임 : 1. 교원동의 2. 학생관리계획 3. 학생소속변경동의서(재적생 전원) 4. 소속변경학생의 교육과정시행\n세칙 변경사항\n* 붙임 자료와 함께 학과 신설을 위한 교수회의록 1부 제출 |  |  |  |  |",
  "metadata": {
    "document_title": "2-1. 경희대학교대학원시행세칙 개정전문_2025.3.1.",
    "sourceFile": "2-1. 경희대학교대학원시행세칙 개정전문_2025.3.1..pdf",
    "page": 26,
    "articleNumber": 33,
    "articleSub": null,
    "articleTitle": "학과·전공 신설 및 폐지",
    "contentType": "table",
    "md5": "b6082de32338650d8bc4482345817204",
    "page_number": 26,
    "article_number": "제33조",
    "article_title": "학과·전공 신설 및 폐지",
    "content_type": "table",
    "text_as_html": null
  }
}