{
  "text": "제75조(경영대학원 운영위원회) ① 본 대학원 운영의 중요사항을 심의하기 위하여 운영위원회를 둔다.\n② 운영위원회는 당연직 2인(대학원장, 부대학원장), 임명직 3인 등 5인 이상의 위원으로 구성한다.\n③ 임명직 위원은 본교 교원으로 본 대학원장이 임명한다.\n④ 당연직 위원의 임기는 보직 재임기간으로 하고, 임명직 위원의 임기는 2년으로 하되 연임할 수 있다.\n⑤ 본 대학원장은 운영위원회 위원장이 되며, 위원장은 운영위원회 회의를 소집하고 그 의장이 된다. 위원장\n이 그 직무를 수행할 수 없을 때에는 부대학원장이 그 직무를 대행한다.\nKoo\noe\nHo\n⑥ 운영위원회 회의는 재적위원 과반수의 출석으로 성원하고, 출석위원 과반수의 찬성으로 의결한다.\n⑦ 간사를 별도로 두어 운영할 수 있다.",
  "metadata": {
    "document_title": "경영대학원내규_20250301_개정",
    "sourceFile": "경영대학원내규_20250301_개정.pdf",
    "page": 11,
    "articleNumber": 75,
    "articleSub": null,
    "articleTitle": "경영대학원 운영위원회",
    "contentType": "text",
    "md5": "cb676b3c48dea54f88101a3d03dfcfcd",
    "page_number": 11,
    "article_number": "제75조",
    "article_title": "경영대학원 운영위원회",
    "content_type": "text"
  }
}