{
  "text": "제1조(목적) 본 규정은 경희대학교(이하 ‘본교’) 의학계열 학술 및 연구 진흥을 위해 경희대학교 처무규 정 제8조에 따라 설치한 경희의과학연구원(이하 ‘연구원’)의 조직과 운영에 관한 사항을 규정함을 목적으 로 한다.",
  "metadata": {
    "document_title": "경희대학교 경희의과학연구원 운영규정 제정_전문.",
    "sourceFile": "경희대학교 경희의과학연구원 운영규정 제정_전문..pdf",
    "page": 1,
    "articleNumber": 1,
    "articleSub": null,
    "articleTitle": "목적",
    "contentType": "text",
    "md5": "d34d6518b958d6b100ea4a0b72b0261b",
    "page_number": 1,
    "article_number": "제1조",
    "article_title": "목적",
    "content_type": "text"
  }
}