{
  "text": "제2조(편제개편에 관한 경과조치) ① 정경대학 언론정보학과, 자율전공학과 글로벌리더전공, 글로벌비즈 니스전공을 수료한 자는 2021년 3월 1일부로 각각 정경대학 미디어학과, 자율전공학부 글로벌리더전\n공, 글로벌비즈니스전공으로 소속을 변경한다.\n② 이 학칙 시행 당시 생명과학대학 원예생명공학과 재적 중인 자는 2022년 3월 1일부로 생명과학대 학 스마트팜과학과로 소속을 변경한다. 다만, 이 학칙 개정 이전에 입학한 학생이 생명과학대학 원예 생명공학과 소속으로 졸업을 원할 경우 2026학년도까지 이를 인정한다.",
  "metadata": {
    "document_title": "경희대학교학칙_개정 전문 2025.04.30.",
    "sourceFile": "경희대학교학칙_개정 전문 2025.04.30..pdf",
    "page": 33,
    "articleNumber": 2,
    "articleSub": null,
    "articleTitle": "편제개편에 관한 경과조치",
    "contentType": "text",
    "md5": "b2e9f1d5cc2a750904d8115e2bfcb4a8",
    "page_number": 33,
    "article_number": "제2조",
    "article_title": "편제개편에 관한 경과조치",
    "content_type": "text"
  }
}