{
  "text": "| 단과대학(학과) |  | 입학년도별 졸업필요학점 |  |  |  |  |  |  |  |\n| --- | --- | --- | --- | --- | --- | --- | --- | --- | --- |\n|  |  | 2025 | 2024 | 2023 | 2022 | 2021 | 2020 | 2019 | 2018 |\n|  |  | 120 | 120 | 130 | 130 | 130 | 130 | 130 | 130 |\n|  |  | 120 | 120 | 120 | 120 | 120 | 120 | 120 | 120 |\n|  |  | 120 | 120 | 120 | 120 | 120 | 120 | 120 | 120 |\n|  | Hospitality경영학부 | - | - | - | 120 | 120 | 120 | 120 |  |\n|  | Hospitality경영학과 | 120 | 120 | 120 | - | - | - | - |  |\n|  | 조리&푸드디자인학과 | 120 | 120 | 120 | - | - | - | - |  |\n|  | 관광학부 | - | - | - | 120 | 120 | 120 | 120 |  |\n|  | 관광·엔터테인먼트학부 | 120 | 120 | 120 | - | - | - | - |  |\n|  | 글로벌Hospitality·관광학과 | 120 | 120 | - | - | - | - | - |  |\n|  | 문화관광산업학과 | 120 | 120 | 120 | 120 | 120 | 120 | 120 |  |\n|  | 조리산업학과 | 120 | 120 | 120 | 120 | 120 | 120 | 120 |  |\n|  |  | 130 | 130 | 130 | 130 | 130 | 130 | 130 | 130 |\n|  | 아동가족학과 | 120 | 120 | 130 | 130 | 130 | 130 | 130 | 130 |\n|  | 주거환경학과 | 120 | 120 | 130 | 130 | 130 | 130 | 130 | 130 |\n|  | 의상학과 | 120 | 120 | 130 | 130 | 130 | 130 | 130 | 130 |\n|  | 식품영양학과 | 130 | 130 | 130 | 130 | 130 | 130 | 130 | 130 |\n|  | 의예과 | 81(수료) | 81(수료) | 80(수료) | 80(수료) | 80(수료) | 80(수료) | 80(수료) |  |\n|  | 의학과 | 181 | 181 | 181 | 181 | 181 | 181 | 182 |  |\n|  | 한의예과 | 76(수료) | 76(수료) | 76(수료) | 76(수료) | 76(수료) | 76(수료) | 75(수료) |  |\n|  | 한의학과 | 168 | 168 | 168 | 168 | 168 | 168 | 169 |  |\n|  | 치의예과 | 67(수료) | 67(수료) | 73(수료) | 73(수료) | 73(수료) | 73(수료) | 73(수료) |  |\n|  | 치의학과 | 174.5 | 174.5 | 174.5 | 174.5 | 174.5 | 174.5 | 174.5 |  |\n|  | 약학과 | 254 | 254 | 254 | 254 | - | - | - |  |\n|  | 약학과(2+4년제) | - | - | - | - | 155 | 155 | 155 |  |\n|  | 한약학과 | 150 | 150 | 150 | 150 | 150 | 150 | 150 |  |\n|  | 약과학과 | 130 | 130 | 130 | 130 | 130 | 130 | 130 |  |\n|  | 간호학과 | 130 | 130 | 131 | 131 | 131 | 131 | 131 |  |\n|  | 간호학과(야) | 120 | 120 | 120 | 120 | 120 | 120 | 120 |  |\n|  |  | 120 | 120 | 120 | 120 | 120 | 120 | 120 | 120 |\n|  |  | 120 | 120 | 120 | 120 | 120 | 120 | 120 | 120 |\n|  |  | 120 | 120 | 120 | 120 | 120 | 120 | 120 | 120 |\n|  |  | 120 | 120 | 120 | 120 | 120 | 120 | 130 | 130 |\n|  | 건축학과 외 | 130 | 130 | 130 | 130 | 130 | 130 | 130 | 130 |\n|  | 건축학과 | 165 | 165 | 165 | 165 | 165 | 165 | 165 | 165 |\n|  |  | 130 | 130 | 130 | 130 | 130 | 130 | 130 | 130 |\n|  | 컴퓨터공학과 | - | - | - | - | 140 | 140 | 140 |  |\n|  | 컴퓨터공학부\n컴퓨터공학과 | 130 | 130 | 140 | 140 | - | - | - |  |\n|  | 컴퓨터공학부\n인공지능학과 | 130 | 130 | 130 | 130 | - | - | - |  |\n|  | 소프트웨어\n융합학과 | 130 | 130 | 130 | 130 | 130 | 130 | 130 |  |\n|  |  | 130 | 130 | 130 | 130 | 130 | 130 | 130 | 130 |\n|  |  | 130 | 130 | 130 | 130 | 130 | 130 | 130 | 130 |\n|  |  | 120 | 120 | 120 | 120 | 120 | 120 | 120 | 120 |",
  "metadata": {
    "document_title": "경희대학교학칙_개정 전문 2025.04.30.",
    "sourceFile": "경희대학교학칙_개정 전문 2025.04.30..pdf",
    "page": 42,
    "articleNumber": 1,
    "articleSub": null,
    "articleTitle": "시행일",
    "contentType": "table",
    "md5": "1169fa67f91ece5c578a32c8029f7a2a",
    "page_number": 42,
    "article_number": "제1조",
    "article_title": "시행일",
    "content_type": "table",
    "text_as_html": null
  }
}