{
  "text": "제16조 (수입) 다음 각 호의 수입을 산학협력단의 수입으로 한다.\n1. 국고 또는 지방자치단체로부터의 출연금 및 보조금\nsb ot El hh\n2. 산학연협력계약에 의한 수입금, 유가증권, 그 밖에 재산적 가치가 있는 물건\n3. 산학연협력 성과에 의한 수익금, 유가증권, 그 밖에 재산적 가치가 있는 물건\n4. 산학연협력과 관련하여 접수한 기부금품\n5. 산학협력단이 설치한 학교기업으로부터의 운영 수익금\n6. 이자수입 등 기타의 수입\n7. 산학협력단 소유의 연구시설과 실험실습시설 및 장비에 대한 사용료\n8. 기술지주회사로부터의 배당 및 그 밖의 수익금",
  "metadata": {
    "document_title": "경희대학교산학협력단정관_20240820_개정",
    "sourceFile": "경희대학교산학협력단정관_20240820_개정.pdf",
    "page": 3,
    "articleNumber": 16,
    "articleSub": null,
    "articleTitle": "수입",
    "contentType": "text",
    "md5": "d84f5b551934a07645c5170b33819210",
    "page_number": 3,
    "article_number": "제16조",
    "article_title": "수입",
    "content_type": "text"
  }
}