{
  "text": "제21조(위험시의 조치) ① 아래와 같은 사항이 발생한 때에는 지체없이 대피, 소화, 피난, 오염제거 및 일반 인의 접근을 금지하는 등 방사선 장해방어에 필요한 모든 조치를 강구하는 동시에 재해 또는 사고 발생의 일시, 장소, 원인, 상황, 안전조치의 내용에 관하여 교육과학기술부장관 및 한국원자력안전기술원장에게 지 체없이 보고한다. 또한 아래 제2호 및 제7호의 사고가 발생한 때에는 그 지역을 관할하는 경찰서에 즉시 신고하여야 하며 이외의 사고 등은 안전조치를 취하는데 필요한 관련기관에도 즉시 신고하여야 한다.\n1. 방사선 관계시설에 화재가 발생하거나 이에 의한 연소가 있을 경우\n2. 방사성동위원소 등이 도난, 소재불명이 될 때\naye)\n3. 방사성물질 등에 의하여 오염이 발생되는 경우\n4. 방사선작업종사자 또는 수시 출입자가 교육과학기술부장관이 정하는 선량한도를 초과하여 피폭된 때\n5. 방사선 관계시설로 인하여 인체의 장해가 발생하거나 발생의 우려가 있는 때\n6. 방사성물질 등의 운반에 있어 장해 또는 사고가 발생된 때\n“\n7. 방사성물질이 누출되어 인근주민의 긴급 대피가 필요한 때\n8. 기타 관계 법령에서 정한 사고 등이 발생한 때",
  "metadata": {
    "document_title": "경희대학교서울캠퍼스방사선안전관리규정_20111001_개정",
    "sourceFile": "경희대학교서울캠퍼스방사선안전관리규정_20111001_개정.pdf",
    "page": 10,
    "articleNumber": 21,
    "articleSub": null,
    "articleTitle": "위험시의 조치",
    "contentType": "text",
    "md5": "a57151896fe688d3d7f21299e32f58c8",
    "page_number": 10,
    "article_number": "제21조",
    "article_title": "위험시의 조치",
    "content_type": "text"
  }
}