{
  "text": "| 특수대학원 | 과정 | 학 과 | 전 공 | 학위종별 | 입학정원 |\n| --- | --- | --- | --- | --- | --- |\n| 아트ㆍ퓨전\n디자인대학원 | 석사 | 실용음악학과 | 실용음악 | 음악학석사 |  |\n|  |  | 문화예술콘텐츠학과 | 문화예술콘텐츠 | 예술학석사 |  |\n|  |  | 미디어엔터테인먼트학과 | 엔터테이너, 크리에이터 | 예술학석사 |  |\n| 간호\n대학원 | 석사 | 간호학과 | 노인전문간호사전공 | 간호학석사 |  |\n|  |  |  | 정신전문간호사전공 |  |  |\n|  |  |  | 임상간호전문가전공 |  |  |\n| 계 |  |  |  |  | 975명 |",
  "metadata": {
    "document_title": "경희대학교대학원학칙 개정 전문_2025.3.1",
    "sourceFile": "경희대학교대학원학칙 개정 전문_2025.3.1.pdf",
    "page": 32,
    "articleNumber": 24,
    "articleSub": null,
    "articleTitle": "학기당 취득학점",
    "contentType": "table",
    "md5": "6450ead3b43e6d4c59dc5939b7293c26",
    "page_number": 32,
    "article_number": "제24조",
    "article_title": "학기당 취득학점",
    "content_type": "table",
    "text_as_html": null
  }
}